setup.py
vecnet/__init__.py
vecnet.emod.egg-info/PKG-INFO
vecnet.emod.egg-info/SOURCES.txt
vecnet.emod.egg-info/dependency_links.txt
vecnet.emod.egg-info/namespace_packages.txt
vecnet.emod.egg-info/top_level.txt
vecnet/emod/scripts/generate_sweeps.bat
vecnet/emod/__init__.py
vecnet/emod/climate.py
vecnet/emod/demographics.py
vecnet/emod/eir.py
vecnet/emod/experiment.py
vecnet/emod/input.py
vecnet/emod/koppen.py
vecnet/emod/migration.py
vecnet/emod/nodeid.py
vecnet/emod/run.py
vecnet/emod/bin/__init__.py
vecnet/emod/bin/buildCsvFile.py
vecnet/emod/bin/buildEmodFiles.py
vecnet/emod/bin/plot_weather_from_output.py
vecnet/emod/output/__init__.py
vecnet/emod/output/binnedreport.py
vecnet/emod/output/output.py
vecnet/emod/scripts/generate_sweeps.bat
vecnet/emod/tests/__init__.py
vecnet/emod/tests/tests.py
vecnet/emod/tests/tests_climate.py
vecnet/emod/tests/tests_output.py