Metadata-Version: 1.1
Name: vecnet.emod
Version: 0.7.3
Summary: Python package for loading EMOD weather files, store the data in memory so that it can be modified, and saves the data to weather files. Allows for conversions between nodeIDs and latitude and longitude pairs.
Home-page: https://github.com/vecnet/vecnet.emod
Author: University of Notre Dame, Center for Research Computing
Author-email: khostetl@nd.edu
License: MPL 2.0
Keywords: weather data climate file malaria converter conversion node id nodeid latitude longitude
Platform: UNKNOWN
Classifier: Development Status :: 3 - Alpha
Classifier: License :: OSI Approved :: Mozilla Public License 2.0 (MPL 2.0)
Classifier: Intended Audience :: Developers
Classifier: Operating System :: OS Independent
Classifier: Programming Language :: Python
Classifier: Programming Language :: Python :: 2
Classifier: Programming Language :: Python :: 2.7
Classifier: Topic :: Software Development :: Libraries :: Python Modules
